opensr_degradation/__init__.py
opensr_degradation/datamodel.py
opensr_degradation/main.py
opensr_degradation/naipd/blur.py
opensr_degradation/naipd/harmonization.py
opensr_degradation/naipd/main.py
opensr_degradation/naipd/models/model_noise.pt
opensr_degradation/naipd/models/model_unet.pt
opensr_degradation/naipd/models/model_vae.pt
opensr_degradation/naipd/noise.py
opensr_degradation/swinir.py
opensr_degradation/utils.py
opensr_degradation-1.0.1.dist-info/WHEEL
opensr_degradation-1.0.1.dist-info/METADATA
opensr_degradation-1.0.1.dist-info/RECORD
